svg2ssa/__init__.py
svg2ssa/__main__.py
svg2ssa/attributes/__init__.py
svg2ssa/attributes/color.py
svg2ssa/attributes/d.py
svg2ssa/attributes/misc.py
svg2ssa/attributes/opacity.py
svg2ssa/attributes/transform.py
svg2ssa/core.py
svg2ssa/document.py
svg2ssa/elements.py
svg2ssa/utilities.py
svg2ssa-2022.12.23.0.dist-info/LICENSE
svg2ssa-2022.12.23.0.dist-info/METADATA
svg2ssa-2022.12.23.0.dist-info/WHEEL
svg2ssa-2022.12.23.0.dist-info/RECORD
