Metadata-Version: 2.1
Name: svg2ssa
Version: 2022.12.23.0
Summary: Converts subset of SVG 1.1 to SSA v4+
Home-page: https://github.com/8day/svg2ssa
License: BSD-3-Clause
Author: 8day
Requires-Python: >=3.7,<4.0
Classifier: Development Status :: 5 - Production/Stable
Classifier: Environment :: Console
Classifier: Intended Audience :: End Users/Desktop
Classifier: License :: OSI Approved :: BSD License
Classifier: Programming Language :: Python :: 3
Classifier: Programming Language :: Python :: 3.7
Classifier: Programming Language :: Python :: 3.8
Classifier: Programming Language :: Python :: 3.9
Classifier: Programming Language :: Python :: 3.10
Classifier: Programming Language :: Python :: 3.11
Classifier: Topic :: Multimedia :: Graphics :: Graphics Conversion
Classifier: Topic :: Utilities
Provides-Extra: fast-parsing
Requires-Dist: defusedxml (>=0.7,<0.8)
Requires-Dist: lxml (>=4.0,<5.0) ; extra == "fast-parsing"
Requires-Dist: ply (>=3.4,<4.0)
